MANIFEST.in
README.md
build.py
requirements-dev.txt
requirements.txt
setup.py
ascii_art/__init__.py
ascii_art/__main__.py
ascii_art/image.py
ascii_art/video.py
pyasciiartist.egg-info/PKG-INFO
pyasciiartist.egg-info/SOURCES.txt
pyasciiartist.egg-info/dependency_links.txt
pyasciiartist.egg-info/requires.txt
pyasciiartist.egg-info/top_level.txt